pynexus/__init__.py
pynexus/jsocket.py
pynexus/net.py
pynexus/pynexus.py
pynexus/version.py
pynexus2-1.4.0.dist-info/COPYING
pynexus2-1.4.0.dist-info/METADATA
pynexus2-1.4.0.dist-info/WHEEL
pynexus2-1.4.0.dist-info/top_level.txt
pynexus2-1.4.0.dist-info/RECORD
