Metadata-Version: 2.1
Name: pynexus2
Version: 1.4.0
Summary: A Python library for easy playing with Nexus
Home-page: https://github.com/jaracil/nxpy
Author: Nayar Systems
Author-email: prod@nayarsystems.com
License: LGPLv3+
Keywords: nexus distributed microservices
Classifier: Development Status :: 4 - Beta
Classifier: Intended Audience :: Developers
Classifier: Topic :: Software Development :: Libraries :: Python Modules
Classifier: License :: OSI Approved :: GNU Lesser General Public License v3 or later (LGPLv3+)
Classifier: Programming Language :: Python :: 2.6
Classifier: Programming Language :: Python :: 2.7
Classifier: Programming Language :: Python :: 3
Classifier: Programming Language :: Python :: 3.2
Classifier: Programming Language :: Python :: 3.3
Classifier: Programming Language :: Python :: 3.4
Classifier: Programming Language :: Python :: 3.5
License-File: COPYING
Requires-Dist: srvlookup
Requires-Dist: websocket-client
